scgpt/__init__.py
scgpt/data_collator.py
scgpt/data_sampler.py
scgpt/loss.py
scgpt/model/__init__.py
scgpt/model/dsbn.py
scgpt/model/generation_model.py
scgpt/model/grad_reverse.py
scgpt/model/model.py
scgpt/model/multiomic_model.py
scgpt/preprocess.py
scgpt/scbank/__init__.py
scgpt/scbank/data.py
scgpt/scbank/databank.py
scgpt/scbank/monitor.py
scgpt/scbank/setting.py
scgpt/tasks/__init__.py
scgpt/tasks/cell_emb.py
scgpt/tasks/grn.py
scgpt/tokenizer/__init__.py
scgpt/tokenizer/default_census_vocab.json
scgpt/tokenizer/default_gene_vocab.json
scgpt/tokenizer/gene_tokenizer.py
scgpt/trainer.py
scgpt/utils/__init__.py
scgpt/utils/util.py
scgpt-0.2.4.dist-info/LICENSE
scgpt-0.2.4.dist-info/WHEEL
scgpt-0.2.4.dist-info/METADATA
scgpt-0.2.4.dist-info/RECORD
