Metadata-Version: 2.1
Name: scgpt
Version: 0.2.4
Summary: Large-scale generative pretrain of single cell using transformer.
Home-page: https://github.com/bowang-lab/scGPT
License: MIT
Author: Haotian
Author-email: subercui@gmail.com
Requires-Python: >=3.7.12,<4
Classifier: License :: OSI Approved :: MIT License
Classifier: Programming Language :: Python :: 3
Classifier: Programming Language :: Python :: 3.8
Classifier: Programming Language :: Python :: 3.9
Classifier: Programming Language :: Python :: 3.10
Requires-Dist: cell-gears (<0.0.3)
Requires-Dist: datasets (>=2.3.0,<3.0.0)
Requires-Dist: leidenalg (>=0.8.10)
Requires-Dist: numba (>=0.55.1)
Requires-Dist: orbax (<0.1.8)
Requires-Dist: pandas (>=1.3.5)
Requires-Dist: scanpy (>=1.9.1,<2.0.0)
Requires-Dist: scib (>=1.0.3,<2.0.0)
Requires-Dist: scikit-misc (>=0.1.4)
Requires-Dist: scvi-tools (>=0.16.0,<1.0)
Requires-Dist: torch (>=1.13.0)
Requires-Dist: torchtext
Requires-Dist: typing-extensions (>=4.2.0,<5.0.0)
Requires-Dist: umap-learn (>=0.5.3)
Project-URL: Repository, https://github.com/bowang-lab/scGPT
